alu.v
module alu(A, B, O, CTR, ck);
  input [7:0] A, B;
  input [3:0] CTR;
  input ck;
  output [7:0] O;
  reg [7:0] INA, INB, O;
  reg [3:0] C;
  wire [7:0] OUT;

  always @(posedge ck) begin
    INA <= A;
    INB <= B;
    C <= CTR;
    O <= OUT;
  end

  assign OUT =
    (C == 'b0000 ? INA + INB :
    (C == 'b0001 ? INA - INB :
    (C == 'b1000 ? INA & INB :
    (C == 'b1001 ? INA | INB :
    (C == 'b1010 ? INA ^ INB :
    (C == 'b1011 ? ~INA :
    (C == 'b1100 ? INA >> 1 :
    (C == 'b1101 ? INA << 1 :
    (C == 'b1110 ? { INA & 8'b10000000, INA >> 1 } :
    (C == 'b1111 ? { INA & 8'b00000001, INA << 1 } : 0
    ))))))))));
endmodule

alutest.v
module  alutest;
reg	[7:0]	A, B;
reg	[3:0]	CTR;
reg	ck;
wire	[7:0] O0;
initial begin
	ck=0;
	$dumpfile("alu.vcd");
	$dumpvars;
	$monitor( "%t\tA=%h, B=%h, CTR=%h(%h), OUT=%h %h", $time, A, B, C, CC, O, O0 );
   #1000
     $display( "OK\n" );
   $finish;
end
alu	ALU(A , B , O0 , CTR , ck);
always	#10	ck = ~ck;
always @(negedge ck) begin
	A = $random;
	B = $random;
	CTR  = $random;
end

   reg	[7:0]	INA, INB, OUT, O;
reg	[3:0]	C, CC;

always @(negedge ck) begin
   if( !(O == O0 || ( (CC == 'b0010 || CC== 'b0011 || CC == 'b0100 || CC == 'b0101 || CC=='b0110 || CC == 'b0111) && O0 == 8'b0)) ) $finish;


end



always @(posedge ck) begin
	C <= CTR;
   CC <= C;
	INA <= A;
	INB <= B;
	O <= OUT;
end

always @(C or INA or INB) begin
	case  (C)
	'b0000 : OUT <= INA + INB;
	'b0001 : OUT <= INA - INB;
	'b1000 : OUT <= INA & INB;
	'b1001 : OUT <= INA | INB;
	'b1010 : OUT <= INA ^ INB;
	'b1011 : OUT <= ~INA;
	'b1100 : OUT <= INA>>1;
	'b1101 : OUT <= INA<<1;
	'b1110 : OUT <= {INA[0], INA[7:1]};
	'b1111 : OUT <= {INA[6:0], INA[7]};
//	  default : OUT <= 0;
	endcase
end


endmodule

alu.vcd
$date
	Fri Apr 14 13:37:58 2017
$end
$version
	Icarus Verilog
$end
$timescale
	1s
$end
$scope module alutest $end
$var wire 8 ! O [7:0] $end
$var reg 8 " A [7:0] $end
$var reg 8 # B [7:0] $end
$var reg 4 $ CTR [3:0] $end
$var reg 1 % ck $end
$scope module ALU $end
$var wire 8 & A [7:0] $end
$var wire 8 ' B [7:0] $end
$var wire 4 ( CTR [3:0] $end
$var wire 1 % ck $end
$var wire 8 ) OUT [7:0] $end
$var reg 4 * C [3:0] $end
$var reg 8 + INA [7:0] $end
$var reg 8 , INB [7:0] $end
$var reg 8 - O [7:0] $end
$upscope $end
$upscope $end
$enddefinitions $end
#0
$dumpvars
bx -
bx ,
bx +
bx *
bx )
bx (
bx '
bx &
0%
bx $
bx #
bx "
bx !
$end
#10
1%
#20
b1001 $
b1001 (
b10000001 #
b10000001 '
b100100 "
b100100 &
0%
#30
b10100101 )
b1001 *
b10000001 ,
b100100 +
1%
#40
b1101 $
b1101 (
b1101 #
b1101 '
b1100011 "
b1100011 &
0%
#50
b11000110 )
b10100101 !
b10100101 -
b1101 *
b1101 ,
b1100011 +
1%
#60
b1 $
b1 (
b10010 #
b10010 '
b1100101 "
b1100101 &
0%
#70
b1010011 )
b11000110 !
b11000110 -
b1 *
b10010 ,
b1100101 +
1%
#80
b1101 $
b1101 (
b1110110 #
b1110110 '
b1101 "
b1101 &
0%
#90
b11010 )
b1010011 !
b1010011 -
b1101 *
b1110110 ,
b1101 +
1%
#100
b1001 $
b1001 (
b10001100 #
b10001100 '
b11101101 "
b11101101 &
0%
#110
b11101101 )
b11010 !
b11010 -
b1001 *
b10001100 ,
b11101101 +
1%
#120
b1010 $
b1010 (
b11000101 #
b11000101 '
b11000110 "
b11000110 &
0%
#130
b11 )
b11101101 !
b11101101 -
b1010 *
b11000101 ,
b11000110 +
1%
#140
b10 $
b10 (
b1110111 #
b1110111 '
b11100101 "
b11100101 &
0%
#150
b0 )
b11 !
b11 -
b10 *
b1110111 ,
b11100101 +
1%
