alu.v
module alu(A, B, O, CTR, ck);
  input [7:0] A, B;
  input [3:0] CTR;
  input ck;
  output [7:0] O;
  reg [7:0] INA, INB, O;
  reg [3:0] C;
  wire [7:0] OUT;

  always @(posedge ck) begin
    INA <= A;
    INB <= B;
    C <= CTR;
    O <= OUT;
  end

  assign OUT =
    (C == 'b0000 ? INA + INB :
    (C == 'b0001 ? INA - INB :
    (C == 'b1000 ? INA & INB :
    (C == 'b1001 ? INA | INB :
    (C == 'b1010 ? INA ^ INB :
    (C == 'b1011 ? ~INA :
    (C == 'b1100 ? { 1'b0, INA[7:1] }:
    (C == 'b1101 ? { INA[6:0], 1'b0 }:
    (C == 'b1110 ? { INA[0], INA[7:1] } :
    (C == 'b1111 ? { INA[6:0], INA[7] } : 0
    ))))))))));
endmodule

alutest.v
module  alutest;
reg	[7:0]	A, B;
reg	[3:0]	CTR;
reg	ck;
wire	[7:0] O0;
initial begin
	ck=0;
	$dumpfile("alu.vcd");
	$dumpvars;
	$monitor( "%t\tA=%h, B=%h, CTR=%h(%h), OUT=%h %h", $time, A, B, C, CC, O, O0 );
   #1000
     $display( "OK\n" );
   $finish;
end
alu	ALU(A , B , O0 , CTR , ck);
always	#10	ck = ~ck;
always @(negedge ck) begin
	A = $random;
	B = $random;
	CTR  = $random;
end

   reg	[7:0]	INA, INB, OUT, O;
reg	[3:0]	C, CC;

always @(negedge ck) begin
   if( !(O == O0 || ( (CC == 'b0010 || CC== 'b0011 || CC == 'b0100 || CC == 'b0101 || CC=='b0110 || CC == 'b0111) && O0 == 8'b0)) ) $finish;


end



always @(posedge ck) begin
	C <= CTR;
   CC <= C;
	INA <= A;
	INB <= B;
	O <= OUT;
end

always @(C or INA or INB) begin
	case  (C)
	'b0000 : OUT <= INA + INB;
	'b0001 : OUT <= INA - INB;
	'b1000 : OUT <= INA & INB;
	'b1001 : OUT <= INA | INB;
	'b1010 : OUT <= INA ^ INB;
	'b1011 : OUT <= ~INA;
	'b1100 : OUT <= INA>>1;
	'b1101 : OUT <= INA<<1;
	'b1110 : OUT <= {INA[0], INA[7:1]};
	'b1111 : OUT <= {INA[6:0], INA[7]};
//	  default : OUT <= 0;
	endcase
end


endmodule

alu.vcd
$date
	Fri Apr 21 11:36:31 2017
$end
$version
	Icarus Verilog
$end
$timescale
	1s
$end
$scope module alutest $end
$var wire 8 ! O0 [7:0] $end
$var reg 8 " A [7:0] $end
$var reg 8 # B [7:0] $end
$var reg 4 $ C [3:0] $end
$var reg 4 % CC [3:0] $end
$var reg 4 & CTR [3:0] $end
$var reg 8 ' INA [7:0] $end
$var reg 8 ( INB [7:0] $end
$var reg 8 ) O [7:0] $end
$var reg 8 * OUT [7:0] $end
$var reg 1 + ck $end
$scope module ALU $end
$var wire 8 , A [7:0] $end
$var wire 8 - B [7:0] $end
$var wire 4 . CTR [3:0] $end
$var wire 1 + ck $end
$var wire 8 / OUT [7:0] $end
$var reg 4 0 C [3:0] $end
$var reg 8 1 INA [7:0] $end
$var reg 8 2 INB [7:0] $end
$var reg 8 3 O [7:0] $end
$upscope $end
$upscope $end
$enddefinitions $end
#0
$dumpvars
bx 3
bx 2
bx 1
bx 0
bx /
bx .
bx -
bx ,
0+
bx *
bx )
bx (
bx '
bx &
bx %
bx $
bx #
bx "
bx !
$end
#10
1+
#20
b1001 &
b1001 .
b10000001 #
b10000001 -
b100100 "
b100100 ,
0+
#30
b10100101 *
b10100101 /
b10000001 (
b100100 '
b1001 $
b1001 0
b10000001 2
b100100 1
1+
#40
b1101 &
b1101 .
b1101 #
b1101 -
b1100011 "
b1100011 ,
0+
#50
b11000110 *
b11000110 /
b10100101 !
b10100101 3
b1101 0
b1101 2
b1100011 1
b10100101 )
b1101 (
b1100011 '
b1001 %
b1101 $
1+
#60
b1 &
b1 .
b10010 #
b10010 -
b1100101 "
b1100101 ,
0+
#70
b1010011 *
b1010011 /
b11000110 )
b10010 (
b1100101 '
b1101 %
b1 $
b11000110 !
b11000110 3
b1 0
b10010 2
b1100101 1
1+
#80
b1101 &
b1101 .
b1110110 #
b1110110 -
b1101 "
b1101 ,
0+
#90
b11010 *
b11010 /
b1010011 !
b1010011 3
b1101 0
b1110110 2
b1101 1
b1010011 )
b1110110 (
b1101 '
b1 %
b1101 $
1+
#100
b1001 &
b1001 .
b10001100 #
b10001100 -
b11101101 "
b11101101 ,
0+
#110
b11101101 *
b11101101 /
b11010 )
b10001100 (
b11101101 '
b1101 %
b1001 $
b11010 !
b11010 3
b1001 0
b10001100 2
b11101101 1
1+
#120
b1010 &
b1010 .
b11000101 #
b11000101 -
b11000110 "
b11000110 ,
0+
#130
b11 *
b11 /
b11101101 !
b11101101 3
b1010 0
b11000101 2
b11000110 1
b11101101 )
b11000101 (
b11000110 '
b1001 %
b1010 $
1+
#140
b10 &
b10 .
b1110111 #
b1110111 -
b11100101 "
b11100101 ,
0+
#150
b0 /
b11 )
b1110111 (
b11100101 '
b1010 %
b10 $
b11 !
b11 3
b10 0
b1110111 2
b11100101 1
1+
#160
b1110 &
b1110 .
b11110010 #
b11110010 -
b10001111 "
b10001111 ,
0+
#170
b11000111 *
b11000111 /
b0 !
b0 3
b1110 0
b11110010 2
b10001111 1
b11110010 (
b10001111 '
b10 %
b1110 $
1+
#180
b1100 &
b1100 .
b11000101 #
b11000101 -
b11101000 "
b11101000 ,
0+
#190
b1110100 *
b1110100 /
b11000111 )
b11000101 (
b11101000 '
b1110 %
b1100 $
b11000111 !
b11000111 3
b1100 0
b11000101 2
b11101000 1
1+
#200
b101 &
b101 .
b101101 #
b101101 -
b10111101 "
b10111101 ,
0+
#210
b0 /
b1110100 !
b1110100 3
b101 0
b101101 2
b10111101 1
b1110100 )
b101101 (
b10111101 '
b1100 %
b101 $
1+
#220
b0 &
b0 .
b1010 #
b1010 -
b1100011 "
b1100011 ,
0+
#230
b1101101 *
b1101101 /
b1010 (
b1100011 '
b101 %
b0 $
b0 !
b0 3
b0 0
b1010 2
b1100011 1
1+
#240
b1101 &
b1101 .
b10101010 #
b10101010 -
b100000 "
b100000 ,
0+
#250
b1000000 *
b1000000 /
b1101101 !
b1101101 3
b1101 0
b10101010 2
b100000 1
b1101101 )
b10101010 (
b100000 '
b0 %
b1101 $
1+
#260
b10011 #
b10011 -
b10010110 "
b10010110 ,
0+
#270
b101100 *
b101100 /
b1000000 )
b10011 (
b10010110 '
b1101 %
b1000000 !
b1000000 3
b10011 2
b10010110 1
1+
#280
b101 &
b101 .
b1101011 #
b1101011 -
b1010011 "
b1010011 ,
0+
#290
b0 /
b101100 !
b101100 3
b101 0
b1101011 2
b1010011 1
b101100 )
b1101011 (
b1010011 '
b101 $
1+
#300
b1101 &
b1101 .
b10101110 #
b10101110 -
b10 "
b10 ,
0+
#310
b100 *
b100 /
b10101110 (
b10 '
b101 %
b1101 $
b0 !
b0 3
b1101 0
b10101110 2
b10 1
1+
#320
b1010 &
b1010 .
b100011 #
b100011 -
b11001111 "
b11001111 ,
0+
#330
b11101100 *
b11101100 /
b100 !
b100 3
b1010 0
b100011 2
b11001111 1
b100 )
b100011 (
b11001111 '
b1101 %
b1010 $
1+
#340
b10 &
b10 .
b111100 #
b111100 -
b11001010 "
b11001010 ,
0+
#350
b0 /
b11101100 )
b111100 (
b11001010 '
b1010 %
b10 $
b11101100 !
b11101100 3
b10 0
b111100 2
b11001010 1
1+
#360
b1000 &
b1000 .
b1000001 #
b1000001 -
b10001010 "
b10001010 ,
0+
#370
b0 *
b0 !
b0 3
b1000 0
b1000001 2
b10001010 1
b1000001 (
b10001010 '
b10 %
b1000 $
1+
#380
b1011 &
b1011 .
b10001001 #
b10001001 -
b1111000 "
b1111000 ,
0+
#390
b10000111 *
b10000111 /
b0 )
b10001001 (
b1111000 '
b1000 %
b1011 $
b1011 0
b10001001 2
b1111000 1
1+
#400
b1110 &
b1110 .
b11000110 #
b11000110 -
b10110110 "
b10110110 ,
0+
#410
b1011011 *
b1011011 /
b10000111 !
b10000111 3
b1110 0
b11000110 2
b10110110 1
b10000111 )
b11000110 (
b10110110 '
b1011 %
b1110 $
1+
#420
b1011 &
b1011 .
b101010 #
b101010 -
b10111100 "
b10111100 ,
0+
#430
b1000011 *
b1000011 /
b1011011 )
b101010 (
b10111100 '
b1110 %
b1011 $
b1011011 !
b1011011 3
b1011 0
b101010 2
b10111100 1
1+
#440
b1111 &
b1111 .
b10000101 #
b10000101 -
b1110001 "
b1110001 ,
0+
#450
b11100010 *
b11100010 /
b1000011 !
b1000011 3
b1111 0
b10000101 2
b1110001 1
b1000011 )
b10000101 (
b1110001 '
b1011 %
b1111 $
1+
#460
b1110 &
b1110 .
b111010 #
b111010 -
b111011 "
b111011 ,
0+
#470
b10011101 *
b10011101 /
b11100010 )
b111010 (
b111011 '
b1111 %
b1110 $
b11100010 !
b11100010 3
b1110 0
b111010 2
b111011 1
1+
#480
b1001 &
b1001 .
b11110001 #
b11110001 -
b10101 "
b10101 ,
0+
#490
b11110101 *
b11110101 /
b10011101 !
b10011101 3
b1001 0
b11110001 2
b10101 1
b10011101 )
b11110001 (
b10101 '
b1110 %
b1001 $
1+
#500
b1111 &
b1111 .
b1001100 #
b1001100 -
b1100010 "
b1100010 ,
0+
#510
b11000100 *
b11000100 /
b11110101 )
b1001100 (
b1100010 '
b1001 %
b1111 $
b11110101 !
b11110101 3
b1111 0
b1001100 2
b1100010 1
1+
#520
b111 &
b111 .
b11111000 #
b11111000 -
b10001111 "
b10001111 ,
0+
#530
b0 /
b11000100 !
b11000100 3
b111 0
b11111000 2
b10001111 1
b11000100 )
b11111000 (
b10001111 '
b1111 %
b111 $
1+
#540
b1011 &
b1011 .
b1011100 #
b1011100 -
b10011111 "
b10011111 ,
0+
#550
b1100000 *
b1100000 /
b1011100 (
b10011111 '
b111 %
b1011 $
b0 !
b0 3
b1011 0
b1011100 2
b10011111 1
1+
#560
b0 &
b0 .
b1001001 #
b1001001 -
b10001001 "
b10001001 ,
0+
#570
b11010010 *
b11010010 /
b1100000 !
b1100000 3
b0 0
b1001001 2
b10001001 1
b1100000 )
b1001001 (
b10001001 '
b1011 %
b0 $
1+
#580
b110 &
b110 .
b1010001 #
b1010001 -
b11010111 "
b11010111 ,
0+
#590
b0 /
b11010010 )
b1010001 (
b11010111 '
b0 %
b110 $
b11010010 !
b11010010 3
b110 0
b1010001 2
b11010111 1
1+
#600
b1000 &
b1000 .
b11000010 #
b11000010 -
b1100 "
b1100 ,
0+
#610
b0 *
b0 !
b0 3
b1000 0
b11000010 2
b1100 1
b11000010 (
b1100 '
b110 %
b1000 $
1+
#620
b10 &
b10 .
b111101 #
b111101 -
b1110111 "
b1110111 ,
0+
#630
b0 )
b111101 (
b1110111 '
b1000 %
b10 $
b10 0
b111101 2
b1110111 1
1+
#640
b1001 &
b1001 .
b1101101 #
b1101101 -
b1111110 "
b1111110 ,
0+
#650
b1111111 *
b1111111 /
b1001 0
b1101101 2
b1111110 1
b1101101 (
b1111110 '
b10 %
b1001 $
1+
#660
b101 &
b101 .
b11010011 #
b11010011 -
b11111 "
b11111 ,
0+
#670
b0 /
b1111111 )
b11010011 (
b11111 '
b1001 %
b101 $
b1111111 !
b1111111 3
b101 0
b11010011 2
b11111 1
1+
#680
b1001 &
b1001 .
b1011011 #
b1011011 -
b1111000 "
b1111000 ,
0+
#690
b1111011 *
b1111011 /
b0 !
b0 3
b1001 0
b1011011 2
b1111000 1
b1011011 (
b1111000 '
b101 %
b1001 $
1+
#700
b1000 &
b1000 .
b101010 #
b101010 -
b111111 "
b111111 ,
0+
#710
b101010 *
b101010 /
b1111011 )
b101010 (
b111111 '
b1001 %
b1000 $
b1111011 !
b1111011 3
b1000 0
b101010 2
b111111 1
1+
#720
b1100 &
b1100 .
b10001110 #
b10001110 -
b10000110 "
b10000110 ,
0+
#730
b1000011 *
b1000011 /
b101010 !
b101010 3
b1100 0
b10001110 2
b10000110 1
b101010 )
b10001110 (
b10000110 '
b1000 %
b1100 $
1+
#740
b11 &
b11 .
b100110 #
b100110 -
b11111010 "
b11111010 ,
0+
#750
b0 /
b1000011 )
b100110 (
b11111010 '
b1100 %
b11 $
b1000011 !
b1000011 3
b11 0
b100110 2
b11111010 1
1+
#760
b101111 #
b101111 -
b10100011 "
b10100011 ,
0+
#770
b0 !
b0 3
b101111 2
b10100011 1
b101111 (
b10100011 '
b11 %
1+
#780
b111 &
b111 .
b1000100 #
b1000100 -
b1011111 "
b1011111 ,
0+
#790
b1000100 (
b1011111 '
b111 $
b111 0
b1000100 2
b1011111 1
1+
#800
b1010 &
b1010 .
b11100110 #
b11100110 -
b11001011 "
b11001011 ,
0+
#810
b101101 *
b101101 /
b1010 0
b11100110 2
b11001011 1
b11100110 (
b11001011 '
b111 %
b1010 $
1+
#820
b11101101 #
b11101101 -
b101001 "
b101001 ,
0+
#830
b11000100 *
b11000100 /
b101101 )
b11101101 (
b101001 '
b1010 %
b101101 !
b101101 3
b11101101 2
b101001 1
1+
#840
b1111 &
b1111 .
b10110101 #
b10110101 -
b1100101 "
b1100101 ,
0+
#850
b11001010 *
b11001010 /
b11000100 !
b11000100 3
b1111 0
b10110101 2
b1100101 1
b11000100 )
b10110101 (
b1100101 '
b1111 $
1+
#860
b0 &
b0 .
b1000100 #
b1000100 -
b1111001 "
b1111001 ,
0+
#870
b10111101 *
b10111101 /
b11001010 )
b1000100 (
b1111001 '
b1111 %
b0 $
b11001010 !
b11001010 3
b0 0
b1000100 2
b1111001 1
1+
#880
b1110 &
b1110 .
b10101011 #
b10101011 -
b101010 "
b101010 ,
0+
#890
b10101 *
b10101 /
b10111101 !
b10111101 3
b1110 0
b10101011 2
b101010 1
b10111101 )
b10101011 (
b101010 '
b0 %
b1110 $
1+
#900
b1101 &
b1101 .
b10011010 #
b10011010 -
b11011100 "
b11011100 ,
0+
#910
b10111000 *
b10111000 /
b10101 )
b10011010 (
b11011100 '
b1110 %
b1101 $
b10101 !
b10101 3
b1101 0
b10011010 2
b11011100 1
1+
#920
b1110 &
b1110 .
b1010110 #
b1010110 -
b11000011 "
b11000011 ,
0+
#930
b11100001 *
b11100001 /
b10111000 !
b10111000 3
b1110 0
b1010110 2
b11000011 1
b10111000 )
b1010110 (
b11000011 '
b1101 %
b1110 $
1+
#940
b110 &
b110 .
b1010 #
b1010 -
b1100111 "
b1100111 ,
0+
#950
b0 /
b11100001 )
b1010 (
b1100111 '
b1110 %
b110 $
b11100001 !
b11100001 3
b110 0
b1010 2
b1100111 1
1+
#960
b1000 &
b1000 .
b1111001 #
b1111001 -
b111000 "
b111000 ,
0+
#970
b111000 *
b111000 /
b0 !
b0 3
b1000 0
b1111001 2
b111000 1
b1111001 (
b111000 '
b110 %
b1000 $
1+
#980
b100 &
b100 .
b10010011 #
b10010011 -
b10010100 "
b10010100 ,
0+
#990
b0 /
b111000 )
b10010011 (
b10010100 '
b1000 %
b100 $
b111000 !
b111000 3
b100 0
b10010011 2
b10010100 1
1+
